cosmian_lib_sgx/__init__.py
cosmian_lib_sgx/args.py
cosmian_lib_sgx/crypto_lib.py
cosmian_lib_sgx/enclave.py
cosmian_lib_sgx/error.py
cosmian_lib_sgx/import_hook.py
cosmian_lib_sgx/key_info.py
cosmian_lib_sgx/libcs_sgx_crypto.so
cosmian_lib_sgx/reader.py
cosmian_lib_sgx/side.py
cosmian_lib_sgx/utils.py
cosmian_lib_sgx/writer.py
cosmian_lib_sgx-0.2.1.dist-info/METADATA
cosmian_lib_sgx-0.2.1.dist-info/WHEEL
cosmian_lib_sgx-0.2.1.dist-info/top_level.txt
cosmian_lib_sgx-0.2.1.dist-info/RECORD
