Metadata-Version: 2.1
Name: cosmian-lib-sgx
Version: 0.2.1
Summary: Python library for code providers using Cosmian Secure Computation
Home-page: https://cosmian.com
Author: Cosmian Tech
Author-email: tech@cosmian.com
License: MIT
Classifier: Programming Language :: Python :: 3
Classifier: License :: OSI Approved :: MIT License
Classifier: Operating System :: OS Independent
